textbytesencoder/__init__.py
textbytesencoder/textbytesencoder.py
textbytesencoder-0.1.13.dist-info/LICENSE.md
textbytesencoder-0.1.13.dist-info/WHEEL
textbytesencoder-0.1.13.dist-info/METADATA
textbytesencoder-0.1.13.dist-info/RECORD
