Metadata-Version: 2.1
Name: textbytesencoder
Version: 0.1.13
Summary: Module encoding and encrypting text by key
Home-page: https://github.com/D1ffic00lt/textbytesencoder
License: MIT
Author: D1ffic00lt
Author-email: dm.filinov@gmail.com
Requires-Python: >=3.8,<4.0
Classifier: License :: OSI Approved :: MIT License
Classifier: Programming Language :: Python :: 3
Classifier: Programming Language :: Python :: 3.10
Classifier: Programming Language :: Python :: 3.8
Classifier: Programming Language :: Python :: 3.9
Project-URL: Documentation, https://github.com/D1ffic00lt/textbytesencoder/blob/main/README.md
Project-URL: Repository, https://github.com/D1ffic00lt/textbytesencoder
